{
  "BTC": {
    "long_liq": {
      "price": 56521.532068,
      "direction": "SHORT",
      "buildup_usd": 11030210.0058998,
      "avg_entry": 70651.915086,
      "avg_leverage": 5.0
    },
    "short_liq": {
      "price": 84725.010937,
      "direction": "LONG",
      "buildup_usd": 540009.0212598387,
      "avg_entry": 70604.175781,
      "avg_leverage": 5.0
    }
  },
  "ETH": {
    "short_liq": {
      "price": 2567.115926,
      "direction": "LONG",
      "buildup_usd": 27894604.948758367,
      "avg_entry": 2139.263272,
      "avg_leverage": 5.0
    }
  },
  "HYPE": {
    "long_liq": {
      "price": 29.951467,
      "direction": "SHORT",
      "buildup_usd": 1074796.3962992486,
      "avg_entry": 37.439334,
      "avg_leverage": 5.0
    }
  },
  "SOL": {
    "long_liq": {
      "price": 72.611536,
      "direction": "SHORT",
      "buildup_usd": 962825.9428202108,
      "avg_entry": 90.76442,
      "avg_leverage": 5.0
    },
    "short_liq": {
      "price": 108.780301,
      "direction": "LONG",
      "buildup_usd": 157043.53923927393,
      "avg_entry": 90.650251,
      "avg_leverage": 5.0
    }
  },
  "XRP": {
    "long_liq": {
      "price": 1.135411,
      "direction": "SHORT",
      "buildup_usd": 712598.0325999999,
      "avg_entry": 1.419264,
      "avg_leverage": 5.0
    },
    "short_liq": {
      "price": 1.696012,
      "direction": "LONG",
      "buildup_usd": 829646.3946,
      "avg_entry": 1.413343,
      "avg_leverage": 5.0
    }
  },
  "PAXG": {
    "long_liq": {
      "price": 3484.989227,
      "direction": "SHORT",
      "buildup_usd": 1177714.5511999954,
      "avg_entry": 4356.236533,
      "avg_leverage": 5.0
    },
    "short_liq": {
      "price": 5200.81649,
      "direction": "LONG",
      "buildup_usd": 2820081.4004000067,
      "avg_entry": 4334.013742,
      "avg_leverage": 5.0
    }
  },
  "ASTER": {
    "short_liq": {
      "price": 0.770743,
      "direction": "LONG",
      "buildup_usd": 89609.83496,
      "avg_entry": 0.65908,
      "avg_leverage": 5.9
    }
  },
  "ZEC": {
    "long_liq": {
      "price": 184.226174,
      "direction": "SHORT",
      "buildup_usd": 323629.8352000035,
      "avg_entry": 230.282717,
      "avg_leverage": 5.0
    },
    "short_liq": {
      "price": 276.835571,
      "direction": "LONG",
      "buildup_usd": 588288.2171999995,
      "avg_entry": 230.696309,
      "avg_leverage": 5.0
    }
  },
  "ZRO": {
    "long_liq": {
      "price": 1.753941,
      "direction": "SHORT",
      "buildup_usd": 93245.87667996097,
      "avg_entry": 2.192426,
      "avg_leverage": 5.0
    }
  },
  "TAO": {
    "long_liq": {
      "price": 239.171281,
      "direction": "SHORT",
      "buildup_usd": 5476341.759139981,
      "avg_entry": 298.964101,
      "avg_leverage": 5.0
    }
  },
  "AVAX": {
    "long_liq": {
      "price": 7.607902,
      "direction": "SHORT",
      "buildup_usd": 42794.58734202234,
      "avg_entry": 9.509877,
      "avg_leverage": 5.0
    }
  },
  "FARTCOIN": {
    "long_liq": {
      "price": 0.141361,
      "direction": "SHORT",
      "buildup_usd": 82997.03345597791,
      "avg_entry": 0.176702,
      "avg_leverage": 5.0
    }
  },
  "PUMP": {
    "long_liq": {
      "price": 0.001438,
      "direction": "SHORT",
      "buildup_usd": 7451.2863,
      "avg_entry": 0.001792,
      "avg_leverage": 5.1
    },
    "short_liq": {
      "price": 0.002145,
      "direction": "LONG",
      "buildup_usd": 49102.175145999994,
      "avg_entry": 0.001791,
      "avg_leverage": 5.1
    }
  },
  "LIT": {
    "long_liq": {
      "price": 0.762016,
      "direction": "SHORT",
      "buildup_usd": 40838.15956,
      "avg_entry": 0.95252,
      "avg_leverage": 5.0
    }
  },
  "XPL": {
    "long_liq": {
      "price": 0.076438,
      "direction": "SHORT",
      "buildup_usd": 19462.776122,
      "avg_entry": 0.095547,
      "avg_leverage": 5.0
    }
  },
  "LINK": {
    "long_liq": {
      "price": 7.250892,
      "direction": "SHORT",
      "buildup_usd": 48653.438200004224,
      "avg_entry": 9.063615,
      "avg_leverage": 5.0
    }
  },
  "XMR": {
    "long_liq": {
      "price": 305.109467,
      "direction": "SHORT",
      "buildup_usd": 357767.07994000416,
      "avg_entry": 353.868298,
      "avg_leverage": 7.3
    }
  },
  "MON": {
    "long_liq": {
      "price": 0.01709,
      "direction": "SHORT",
      "buildup_usd": 3068.610568,
      "avg_entry": 0.021363,
      "avg_leverage": 5.0
    },
    "short_liq": {
      "price": 0.025637,
      "direction": "LONG",
      "buildup_usd": 23533.758562000003,
      "avg_entry": 0.021364,
      "avg_leverage": 5.0
    }
  },
  "kPEPE": {
    "long_liq": {
      "price": 0.002722,
      "direction": "SHORT",
      "buildup_usd": 488840.28010199993,
      "avg_entry": 0.003402,
      "avg_leverage": 5.0
    }
  },
  "BNB": {
    "long_liq": {
      "price": 508.317924,
      "direction": "SHORT",
      "buildup_usd": 42591.88323999489,
      "avg_entry": 635.397405,
      "avg_leverage": 5.0
    }
  },
  "WLFI": {
    "long_liq": {
      "price": 0.082611,
      "direction": "SHORT",
      "buildup_usd": 25494.096760000004,
      "avg_entry": 0.103264,
      "avg_leverage": 5.0
    },
    "short_liq": {
      "price": 0.122937,
      "direction": "LONG",
      "buildup_usd": 6630.1856,
      "avg_entry": 0.102448,
      "avg_leverage": 5.0
    }
  },
  "WLD": {
    "long_liq": {
      "price": 0.257129,
      "direction": "SHORT",
      "buildup_usd": 27678.089353983218,
      "avg_entry": 0.321411,
      "avg_leverage": 5.0
    }
  },
  "AAVE": {
    "long_liq": {
      "price": 87.698808,
      "direction": "SHORT",
      "buildup_usd": 30823.70319999924,
      "avg_entry": 109.62351,
      "avg_leverage": 5.0
    }
  },
  "DOGE": {
    "long_liq": {
      "price": 0.074836,
      "direction": "SHORT",
      "buildup_usd": 554595.477614,
      "avg_entry": 0.093545,
      "avg_leverage": 5.0
    },
    "short_liq": {
      "price": 0.111879,
      "direction": "LONG",
      "buildup_usd": 477150.295292,
      "avg_entry": 0.093233,
      "avg_leverage": 5.0
    }
  },
  "BCH": {
    "long_liq": {
      "price": 380.125568,
      "direction": "SHORT",
      "buildup_usd": 8232.545060003897,
      "avg_entry": 475.15696,
      "avg_leverage": 5.0
    }
  },
  "SUI": {
    "long_liq": {
      "price": 0.753772,
      "direction": "SHORT",
      "buildup_usd": 234158.08371199828,
      "avg_entry": 0.942215,
      "avg_leverage": 5.0
    }
  },
  "TRUMP": {
    "short_liq": {
      "price": 3.723465,
      "direction": "LONG",
      "buildup_usd": 54700.76676000001,
      "avg_entry": 3.272365,
      "avg_leverage": 7.3
    }
  },
  "NEAR": {
    "long_liq": {
      "price": 1.046602,
      "direction": "SHORT",
      "buildup_usd": 12793.371520002434,
      "avg_entry": 1.308253,
      "avg_leverage": 5.0
    }
  },
  "VIRTUAL": {
    "short_liq": {
      "price": 0.782038,
      "direction": "LONG",
      "buildup_usd": 8481.02348399949,
      "avg_entry": 0.681307,
      "avg_leverage": 6.8
    }
  },
  "LTC": {
    "long_liq": {
      "price": 44.224734,
      "direction": "SHORT",
      "buildup_usd": 46149.41047999878,
      "avg_entry": 55.280918,
      "avg_leverage": 5.0
    }
  },
  "ENA": {
    "long_liq": {
      "price": 0.073683,
      "direction": "SHORT",
      "buildup_usd": 50615.652832,
      "avg_entry": 0.091706,
      "avg_leverage": 5.1
    },
    "short_liq": {
      "price": 0.110658,
      "direction": "LONG",
      "buildup_usd": 19391.414588,
      "avg_entry": 0.092482,
      "avg_leverage": 5.1
    }
  },
  "TRX": {
    "long_liq": {
      "price": 0.247029,
      "direction": "SHORT",
      "buildup_usd": 6096.050140000001,
      "avg_entry": 0.308786,
      "avg_leverage": 5.0
    }
  },
  "ADA": {
    "long_liq": {
      "price": 0.207644,
      "direction": "SHORT",
      "buildup_usd": 41405.172620000005,
      "avg_entry": 0.259555,
      "avg_leverage": 5.0
    }
  },
  "VVV": {
    "long_liq": {
      "price": 4.581238,
      "direction": "SHORT",
      "buildup_usd": 87367.9120880025,
      "avg_entry": 5.726548,
      "avg_leverage": 5.0
    },
    "short_liq": {
      "price": 6.7411,
      "direction": "LONG",
      "buildup_usd": 29308.436035999268,
      "avg_entry": 5.617583,
      "avg_leverage": 5.0
    }
  },
  "UNI": {
    "long_liq": {
      "price": 2.847322,
      "direction": "SHORT",
      "buildup_usd": 23506.70506000199,
      "avg_entry": 3.559152,
      "avg_leverage": 5.0
    }
  },
  "TON": {
    "long_liq": {
      "price": 1.058163,
      "direction": "SHORT",
      "buildup_usd": 5208.277240000733,
      "avg_entry": 1.322704,
      "avg_leverage": 5.0
    }
  },
  "APT": {
    "long_liq": {
      "price": 0.851579,
      "direction": "SHORT",
      "buildup_usd": 11251.683845999922,
      "avg_entry": 1.0413,
      "avg_leverage": 5.5
    },
    "short_liq": {
      "price": 1.246003,
      "direction": "LONG",
      "buildup_usd": 107144.49575200163,
      "avg_entry": 1.053973,
      "avg_leverage": 5.5
    }
  },
  "DOT": {
    "short_liq": {
      "price": 1.605918,
      "direction": "LONG",
      "buildup_usd": 42292.208759997884,
      "avg_entry": 1.418856,
      "avg_leverage": 7.6
    }
  },
  "CRV": {
    "short_liq": {
      "price": 0.257436,
      "direction": "LONG",
      "buildup_usd": 118367.24107599951,
      "avg_entry": 0.21834,
      "avg_leverage": 5.6
    }
  },
  "kBONK": {
    "short_liq": {
      "price": 0.00688,
      "direction": "LONG",
      "buildup_usd": 112186.65192799999,
      "avg_entry": 0.005918,
      "avg_leverage": 6.2
    }
  },
  "MORPHO": {
    "long_liq": {
      "price": 1.328,
      "direction": "SHORT",
      "buildup_usd": 2035.8239999990724,
      "avg_entry": 1.66,
      "avg_leverage": 5.0
    },
    "short_liq": {
      "price": 2.005615,
      "direction": "LONG",
      "buildup_usd": 17194.439639999688,
      "avg_entry": 1.671346,
      "avg_leverage": 5.0
    }
  },
  "CC": {
    "long_liq": {
      "price": 0.117352,
      "direction": "SHORT",
      "buildup_usd": 1561.95558,
      "avg_entry": 0.14669,
      "avg_leverage": 5.0
    },
    "short_liq": {
      "price": 0.175056,
      "direction": "LONG",
      "buildup_usd": 2996.95872,
      "avg_entry": 0.14588,
      "avg_leverage": 5.0
    }
  },
  "WIF": {
    "long_liq": {
      "price": 0.148906,
      "direction": "SHORT",
      "buildup_usd": 11974.106519999998,
      "avg_entry": 0.186132,
      "avg_leverage": 5.0
    }
  },
  "MNT": {
    "long_liq": {
      "price": 0.563333,
      "direction": "SHORT",
      "buildup_usd": 6032.305603999737,
      "avg_entry": 0.704166,
      "avg_leverage": 5.0
    }
  },
  "ETHFI": {
    "long_liq": {
      "price": 0.422139,
      "direction": "SHORT",
      "buildup_usd": 13216.091323998624,
      "avg_entry": 0.527674,
      "avg_leverage": 5.0
    }
  },
  "JUP": {
    "long_liq": {
      "price": 0.123462,
      "direction": "SHORT",
      "buildup_usd": 26547.26212,
      "avg_entry": 0.154328,
      "avg_leverage": 5.0
    }
  },
  "HBAR": {
    "long_liq": {
      "price": 0.073939,
      "direction": "SHORT",
      "buildup_usd": 3227.9690419999997,
      "avg_entry": 0.092424,
      "avg_leverage": 5.0
    }
  },
  "PENDLE": {
    "long_liq": {
      "price": 0.984455,
      "direction": "SHORT",
      "buildup_usd": 5726.981199999999,
      "avg_entry": 1.230569,
      "avg_leverage": 5.0
    },
    "short_liq": {
      "price": 1.469205,
      "direction": "LONG",
      "buildup_usd": 661.1411999999999,
      "avg_entry": 1.224337,
      "avg_leverage": 5.0
    }
  },
  "FET": {
    "long_liq": {
      "price": 0.187211,
      "direction": "SHORT",
      "buildup_usd": 48667.56244000001,
      "avg_entry": 0.234014,
      "avg_leverage": 5.0
    }
  },
  "IP": {
    "short_liq": {
      "price": 0.754843,
      "direction": "LONG",
      "buildup_usd": 5346.511690000976,
      "avg_entry": 0.652958,
      "avg_leverage": 6.4
    }
  },
  "MEGA": {
    "long_liq": {
      "price": 0.112437,
      "direction": "SHORT",
      "buildup_usd": 717.3489199999999,
      "avg_entry": 0.140547,
      "avg_leverage": 5.0
    }
  },
  "LDO": {
    "long_liq": {
      "price": 0.233483,
      "direction": "SHORT",
      "buildup_usd": 7841.447774001303,
      "avg_entry": 0.291854,
      "avg_leverage": 5.0
    }
  },
  "ATOM": {
    "long_liq": {
      "price": 1.428834,
      "direction": "SHORT",
      "buildup_usd": 10027.346363999697,
      "avg_entry": 1.786043,
      "avg_leverage": 5.0
    },
    "short_liq": {
      "price": 2.1438,
      "direction": "LONG",
      "buildup_usd": 1057.9295700002995,
      "avg_entry": 1.7865,
      "avg_leverage": 5.0
    }
  },
  "STRK": {
    "long_liq": {
      "price": 0.029065,
      "direction": "SHORT",
      "buildup_usd": 31017.987653999244,
      "avg_entry": 0.036332,
      "avg_leverage": 5.0
    }
  },
  "STBL": {
    "long_liq": {
      "price": 0.03016,
      "direction": "SHORT",
      "buildup_usd": 623.703824,
      "avg_entry": 0.0377,
      "avg_leverage": 5.0
    }
  },
  "PURR": {
    "long_liq": {
      "price": 0.062007,
      "direction": "SHORT",
      "buildup_usd": 69.44801,
      "avg_entry": 0.077509,
      "avg_leverage": 5.0
    },
    "short_liq": {
      "price": 0.091994,
      "direction": "LONG",
      "buildup_usd": 18746.465507999997,
      "avg_entry": 0.076662,
      "avg_leverage": 5.0
    }
  },
  "OP": {
    "long_liq": {
      "price": 0.096241,
      "direction": "SHORT",
      "buildup_usd": 1623.7904220004193,
      "avg_entry": 0.113047,
      "avg_leverage": 6.7
    },
    "short_liq": {
      "price": 0.129359,
      "direction": "LONG",
      "buildup_usd": 29350.12755999992,
      "avg_entry": 0.112617,
      "avg_leverage": 6.7
    }
  },
  "ICP": {
    "long_liq": {
      "price": 1.914544,
      "direction": "SHORT",
      "buildup_usd": 6492.690399999441,
      "avg_entry": 2.39318,
      "avg_leverage": 5.0
    },
    "short_liq": {
      "price": 2.852587,
      "direction": "LONG",
      "buildup_usd": 9512.419760000219,
      "avg_entry": 2.377156,
      "avg_leverage": 5.0
    }
  },
  "AERO": {
    "short_liq": {
      "price": 0.402664,
      "direction": "LONG",
      "buildup_usd": 22726.75588,
      "avg_entry": 0.349189,
      "avg_leverage": 6.5
    }
  },
  "ARB": {
    "long_liq": {
      "price": 0.077137,
      "direction": "SHORT",
      "buildup_usd": 6769.5281419989215,
      "avg_entry": 0.096421,
      "avg_leverage": 5.0
    }
  },
  "JTO": {
    "short_liq": {
      "price": 0.35724,
      "direction": "LONG",
      "buildup_usd": 182031.62751999998,
      "avg_entry": 0.3435,
      "avg_leverage": 25.0
    }
  }
}
